MANIFEST.in
setup.py
color_palette/__init__.py
color_palette/color.py
color_palette/color_checks.py
color_palette/conversion.py
color_palette/errors.py
color_palette/mixing.py
color_palette/output.py
color_palette/picker.py
color_palette/presets.py
color_palette.egg-info/PKG-INFO
color_palette.egg-info/SOURCES.txt
color_palette.egg-info/dependency_links.txt
color_palette.egg-info/top_level.txt
color_palette/__pycache__/__init__.cpython-37.pyc
color_palette/__pycache__/color.cpython-37.pyc
color_palette/__pycache__/color_checks.cpython-37.pyc
color_palette/__pycache__/conv.cpython-37.pyc
color_palette/__pycache__/conversion.cpython-37.pyc
color_palette/__pycache__/errors.cpython-37.pyc
color_palette/__pycache__/mixing.cpython-37.pyc
color_palette/__pycache__/picker.cpython-37.pyc
color_palette/__pycache__/presets.cpython-37.pyc
docs/README.md
docs/index.rst