Metadata-Version: 2.1
Name: color-palette
Version: 0.2.6.1
Summary: A color palette module
Home-page: https://github.com/SnowballSH/ColorPalette
Author: SnowballSH, one-wq, 12944qwerty
License: UNKNOWN
Download-URL: https://github.com/SnowballSH/ColorPalette/archive/v0.2.6.1.tar.gz
Platform: UNKNOWN
Classifier: Development Status :: 5 - Production/Stable
Classifier: Intended Audience :: Developers
Classifier: License :: OSI Approved :: MIT License
Classifier: Natural Language :: English
Classifier: Operating System :: OS Independent
Classifier: Programming Language :: Python :: 3.6
Classifier: Programming Language :: Python :: 3.7
Classifier: Programming Language :: Python :: 3.8
Classifier: Topic :: Artistic Software
Requires-Python: >=3.6
